pyriak/__init__.py
pyriak/bind.py
pyriak/entity.py
pyriak/entity_manager.py
pyriak/event_key.py
pyriak/events.py
pyriak/py.typed
pyriak/space.py
pyriak/state_manager.py
pyriak/system_manager.py
pyriak/tag_component.py
pyriak-0.5.0.dist-info/LICENSE
pyriak-0.5.0.dist-info/METADATA
pyriak-0.5.0.dist-info/WHEEL
pyriak-0.5.0.dist-info/RECORD
