Metadata-Version: 2.3
Name: pyriak
Version: 0.5.0
Summary: An implementation of Entity Component System architecture
License: MIT
Keywords: ecs,framework,architecture
Author: aatle
Author-email: 168398276+aatle@users.noreply.github.com
Requires-Python: >=3.10
Classifier: Development Status :: 4 - Beta
Classifier: Intended Audience :: Developers
Classifier: License :: OSI Approved :: MIT License
Classifier: Operating System :: OS Independent
Classifier: Programming Language :: Python :: 3
Classifier: Programming Language :: Python :: 3.10
Classifier: Programming Language :: Python :: 3.11
Classifier: Programming Language :: Python :: 3.12
Classifier: Programming Language :: Python :: 3.13
Classifier: Topic :: Software Development :: Libraries :: Python Modules
Classifier: Typing :: Typed
Project-URL: Issues, https://github.com/aatle/pyriak/issues
Project-URL: Repository, https://github.com/aatle/pyriak.git
